loopies_scraper/__init__.py
loopies_scraper/chromedriver_options.py
loopies_scraper/data_manager.py
loopies_scraper/geckodriver_profile.py
loopies_scraper/scraper.py
loopies_scraper/scraper_multiprocess.py
loopies_scraper/user_agent_generator.py
loopies_scraper/webdriver_controller.py
loopies_scraper-0.0.6.dist-info/LICENSE
loopies_scraper-0.0.6.dist-info/METADATA
loopies_scraper-0.0.6.dist-info/WHEEL
loopies_scraper-0.0.6.dist-info/top_level.txt
loopies_scraper-0.0.6.dist-info/RECORD
