Metadata-Version: 2.1
Name: loopies-scraper
Version: 0.0.6
Summary: Web scraper for basic and/or list of pages scraping
Author: tmspsk
Keywords: python,scraper,multiprocess scraper,list,selenium webdriver
Classifier: Development Status :: 1 - Planning
Classifier: Intended Audience :: Developers
Classifier: Programming Language :: Python :: 3
Classifier: Operating System :: Unix
Classifier: Operating System :: Microsoft :: Windows
License-File: LICENSE
Requires-Dist: selenium ==4.9.1
Requires-Dist: fake-useragent ==1.5.1
